assistant_stream/__init__.py
assistant_stream/assistant_stream_chunk.py
assistant_stream/create_run.py
assistant_stream/state_manager.py
assistant_stream/state_proxy.py
assistant_stream/modules/langgraph.py
assistant_stream/modules/langgraph_chunk_merge.py
assistant_stream/modules/text.py
assistant_stream/modules/tool_call.py
assistant_stream/serialization/__init__.py
assistant_stream/serialization/assistant_stream_response.py
assistant_stream/serialization/data_stream.py
assistant_stream/serialization/openai_stream.py
assistant_stream/serialization/stream_encoder.py
assistant_stream-0.0.30.dist-info/METADATA
assistant_stream-0.0.30.dist-info/WHEEL
assistant_stream-0.0.30.dist-info/licenses/LICENSE
assistant_stream-0.0.30.dist-info/RECORD
