Metadata-Version: 2.4
Name: assistant-stream
Version: 0.0.30
Project-URL: Homepage, https://github.com/assistant-ui/assistant-ui
Project-URL: Issues, https://github.com/assistant-ui/assistant-ui/issues
Author-email: Simon Farshid <simon@assistant-ui.com>
License-File: LICENSE
Classifier: License :: OSI Approved :: MIT License
Classifier: Operating System :: OS Independent
Classifier: Programming Language :: Python :: 3
Requires-Python: <4.0,>=3.9
Requires-Dist: starlette>=0.37.2
Provides-Extra: dev
Requires-Dist: pytest<8; extra == 'dev'
Provides-Extra: langgraph
Requires-Dist: langchain-core>=0.3.0; extra == 'langgraph'
